vendetta/__init__.py
vendetta/cli.py
vendetta/models.py
vendetta/py.typed
vendetta/vendetta.py
vendetta-0.0.2.dist-info/entry_points.txt
vendetta-0.0.2.dist-info/LICENSE
vendetta-0.0.2.dist-info/WHEEL
vendetta-0.0.2.dist-info/METADATA
vendetta-0.0.2.dist-info/RECORD
