Metadata-Version: 2.1
Name: vendetta
Version: 0.0.2
Summary: Anonymize CSV datasets
Home-page: https://github.com/anatoly-scherbakov/vendetta
License: MIT
Requires-Python: >=3.6,<3.9
Classifier: Development Status :: 3 - Alpha
Classifier: Intended Audience :: Developers
Classifier: License :: OSI Approved :: MIT License
Classifier: Operating System :: OS Independent
Classifier: Programming Language :: Python :: 3
Classifier: Programming Language :: Python :: 3.6
Classifier: Programming Language :: Python :: 3.7
Classifier: Programming Language :: Python :: 3.8
Classifier: Topic :: Software Development :: Libraries :: Python Modules
Requires-Dist: faker (>=5.5.1,<6.0.0)
Requires-Dist: pydantic (>=1.7.3,<2.0.0)
Requires-Dist: strictyaml (>=1.3.1,<2.0.0)
Requires-Dist: typer (>=0.3.2,<0.4.0)
Project-URL: Repository, https://github.com/anatoly-scherbakov/vendetta
